funcy_bear/__init__.py
funcy_bear/__main__.py
funcy_bear/api.py
funcy_bear/exceptions.py
funcy_bear/injection.py
funcy_bear/py.typed
funcy_bear/sentinels.py
funcy_bear/system_bools.py
funcy_bear/typing_stuffs.py
funcy_bear/_internal/__init__.py
funcy_bear/_internal/_exit_code.py
funcy_bear/_internal/_info.py
funcy_bear/_internal/_version.py
funcy_bear/_internal/_version.pyi
funcy_bear/_internal/cli.py
funcy_bear/_internal/debug.py
funcy_bear/constants/__init__.py
funcy_bear/constants/binary_types.py
funcy_bear/constants/characters.py
funcy_bear/constants/escaping.py
funcy_bear/constants/exceptions.py
funcy_bear/constants/exit_code.py
funcy_bear/constants/file_size.py
funcy_bear/constants/http_status.py
funcy_bear/constants/py_chars.py
funcy_bear/constants/type_constants.py
funcy_bear/context/__init__.py
funcy_bear/context/arg_helpers.py
funcy_bear/context/di/README.md
funcy_bear/context/di/__init__.py
funcy_bear/context/di/_container_meta.py
funcy_bear/context/di/_param.py
funcy_bear/context/di/container.py
funcy_bear/context/di/container_attrs.py
funcy_bear/context/di/plugin_containers.py
funcy_bear/context/di/plugins.py
funcy_bear/context/di/provides.py
funcy_bear/context/di/provides.pyi
funcy_bear/context/di/resources.py
funcy_bear/context/di/types.py
funcy_bear/context/di/wiring.py
funcy_bear/ops/__init__.py
funcy_bear/ops/_di_containers.py
funcy_bear/ops/async_stuffs.py
funcy_bear/ops/binarystuffs.py
funcy_bear/ops/curried_ops.py
funcy_bear/ops/dispatch.py
funcy_bear/ops/func_stuffs.py
funcy_bear/ops/value_stuffs.py
funcy_bear/ops/collections_ops/__init__.py
funcy_bear/ops/collections_ops/dict_stuffs.py
funcy_bear/ops/collections_ops/iter_stuffs.py
funcy_bear/ops/collections_ops/key_counts.py
funcy_bear/ops/math/README.md
funcy_bear/ops/math/__init__.py
funcy_bear/ops/math/general.py
funcy_bear/ops/math/infinity.py
funcy_bear/ops/strings/README.md
funcy_bear/ops/strings/__init__.py
funcy_bear/ops/strings/dot_template.py
funcy_bear/ops/strings/escaping.py
funcy_bear-0.0.26.dist-info/METADATA
funcy_bear-0.0.26.dist-info/WHEEL
funcy_bear-0.0.26.dist-info/entry_points.txt
funcy_bear-0.0.26.dist-info/RECORD
